fnatools/__init__.py
fnatools-0.0.1.dist-info/METADATA
fnatools-0.0.1.dist-info/RECORD
fnatools-0.0.1.dist-info/WHEEL
fnatools-0.0.1.dist-info/top_level.txt
